pokemail/__init__.py
pokemail/pokemail.py
Pokemail-0.0.1.dist-info/LICENSE
Pokemail-0.0.1.dist-info/METADATA
Pokemail-0.0.1.dist-info/WHEEL
Pokemail-0.0.1.dist-info/top_level.txt
Pokemail-0.0.1.dist-info/RECORD
